MANIFEST.in
README.txt
setup.cfg
setup.py
collective/__init__.py
collective/__init__.pyc
collective.googlelibraries.egg-info/PKG-INFO
collective.googlelibraries.egg-info/SOURCES.txt
collective.googlelibraries.egg-info/dependency_links.txt
collective.googlelibraries.egg-info/entry_points.txt
collective.googlelibraries.egg-info/namespace_packages.txt
collective.googlelibraries.egg-info/not-zip-safe
collective.googlelibraries.egg-info/paster_plugins.txt
collective.googlelibraries.egg-info/requires.txt
collective.googlelibraries.egg-info/top_level.txt
collective/googlelibraries/__init__.py
collective/googlelibraries/__init__.pyc
collective/googlelibraries/apikey.py
collective/googlelibraries/apikey.pyc
collective/googlelibraries/config.py
collective/googlelibraries/config.pyc
collective/googlelibraries/configure.zcml
collective/googlelibraries/controlpanel.py
collective/googlelibraries/controlpanel.pyc
collective/googlelibraries/googleapi.py
collective/googlelibraries/googleapi.pyc
collective/googlelibraries/interfaces.py
collective/googlelibraries/interfaces.pyc
collective/googlelibraries/libraries.py
collective/googlelibraries/libraries.pyc
collective/googlelibraries/scripts.py
collective/googlelibraries/scripts.pyc
collective/googlelibraries/locales/collective.googlelibraries.pot
collective/googlelibraries/locales/fr/LC_MESSAGES/collective.googlelibraries.mo
collective/googlelibraries/locales/fr/LC_MESSAGES/collective.googlelibraries.po
collective/googlelibraries/profiles/default/browserlayer.xml
collective/googlelibraries/profiles/default/controlpanel.xml
collective/googlelibraries/profiles/default/metadata.xml
collective/googlelibraries/profiles/default/propertiestool.xml
collective/googlelibraries/tests/__init__.py
collective/googlelibraries/tests/__init__.pyc
collective/googlelibraries/tests/base.py
collective/googlelibraries/tests/base.pyc
collective/googlelibraries/tests/test_apikey.py
collective/googlelibraries/tests/test_apikey.pyc
collective/googlelibraries/tests/test_controlpanel.txt
collective/googlelibraries/tests/test_googleapi.py
collective/googlelibraries/tests/test_googleapi.pyc
collective/googlelibraries/tests/test_libraries.py
collective/googlelibraries/tests/test_libraries.pyc
collective/googlelibraries/tests/test_scripts.py
collective/googlelibraries/tests/test_scripts.pyc
collective/googlelibraries/tests/test_setup.py
collective/googlelibraries/tests/test_setup.pyc
docs/HISTORY.txt
docs/INSTALL.txt
