Metadata-Version: 1.0
Name: collective.googlelibraries
Version: 1.0b1
Summary: The Libraries API is a content distribution network and loading architecture for the most popular, open-source JavaScript libraries.
Home-page: https://github.com/collective/collective.googlelibraries
Author: JeanMichel FRANCOIS
Author-email: toutpt@makina-corpus.org
License: GPL
Platform: UNKNOWN
Classifier: Framework :: Plone
Classifier: Programming Language :: Python
